Metadata-Version: 1.0
Name: mengyu-distributions
Version: 1.1
Summary: All kinds of distributions
Home-page: UNKNOWN
Author: UNKNOWN
Author-email: UNKNOWN
License: UNKNOWN
Platform: UNKNOWN
